pyprocessors_mazars_table/__init__.py
pyprocessors_mazars_table/mazars_table.py
pyprocessors_mazars_table/normalizers.py
pyprocessors_mazars_table/reducers.py
pyprocessors_mazars_table-0.5.86.dist-info/entry_points.txt
pyprocessors_mazars_table-0.5.86.dist-info/WHEEL
pyprocessors_mazars_table-0.5.86.dist-info/METADATA
pyprocessors_mazars_table-0.5.86.dist-info/RECORD
