Metadata-Version: 2.1
Name: pyprocessors-mazars_table
Version: 0.5.86
Summary: Sherpa Mazars normalizer
Home-page: https://kairntech.com/
Author: Olivier Terrier
Author-email: olivier.terrier@kairntech.com
Requires-Python: >=3.8
Classifier: Intended Audience :: Information Technology
Classifier: Intended Audience :: System Administrators
Classifier: Operating System :: OS Independent
Classifier: Programming Language :: Python :: 3
Classifier: Programming Language :: Python
Classifier: Topic :: Internet
Classifier: Topic :: Software Development :: Libraries :: Application Frameworks
Classifier: Topic :: Software Development :: Libraries :: Python Modules
Classifier: Topic :: Software Development :: Libraries
Classifier: Topic :: Software Development
Classifier: Typing :: Typed
Classifier: Development Status :: 4 - Beta
Classifier: Environment :: Web Environment
Classifier: Framework :: AsyncIO
Classifier: Intended Audience :: Developers
Classifier: Programming Language :: Python :: 3 :: Only
Classifier: Programming Language :: Python :: 3.8
Classifier: Topic :: Internet :: WWW/HTTP :: HTTP Servers
Classifier: Topic :: Internet :: WWW/HTTP
Requires-Dist: pymultirole_plugins>=0.5.0,<0.6.0
Requires-Dist: pandas>=1.2.3,<=1.3.5
Requires-Dist: openpyxl==3.0.7
Requires-Dist: pytest
Requires-Dist: python-Levenshtein
Requires-Dist: thefuzz
Requires-Dist: spacy==3.4.4
Requires-Dist: textacy>=0.11.0
Requires-Dist: pyduckling-native
Requires-Dist: python-singleton-metaclasses
